{
    "flakes": {
        "dwarffs": {
            "uri": "github:edolstra/dwarffs"
        },
        "nix": {
            "uri": "github:NixOS/nix/flakes"
        },
        "nixpkgs": {
            "uri": "github:edolstra/nixpkgs"
        },
        "hydra": {
            "uri": "github:NixOS/hydra/flake"
        },
        "patchelf": {
            "uri": "github:NixOS/patchelf"
        },
        "blender-bin": {
            "uri": "github:edolstra/nix-warez?dir=blender"
        },
        "nixos-homepage": {
            "uri": "github:NixOS/nixos-homepage/flake"
        },
        "nixops": {
            "uri": "github:NixOS/nixops/flake-support"
        }
    },
    "version": 1
}
